{"cameraMode":{"drawMode":0,"name":"Shaded","section":"Shading Mode"},"sceneLighting":true,"audioPlay":false,"sceneViewState":{"showFog":true,"showMaterialUpdate":false,"showSkybox":true,"showFlares":true,"showImageEffects":true,"showParticleSystems":true},"in2DMode":false,"pivot":{"x":-0.5341082811355591,"y":-6.076813220977783,"z":-15.206927299499512},"rotation":{"x":0.0002841388632077724,"y":-0.9818311333656311,"z":0.1902492344379425,"w":0.0017731331754475833},"size":9.493485450744629,"orthographic":false}